ubirch/__init__.py
ubirch/anchoring.py
ubirch_python_utils-1.3.10.dist-info/LICENSE
ubirch_python_utils-1.3.10.dist-info/METADATA
ubirch_python_utils-1.3.10.dist-info/WHEEL
ubirch_python_utils-1.3.10.dist-info/top_level.txt
ubirch_python_utils-1.3.10.dist-info/RECORD
