Metadata-Version: 2.1
Name: ubirch-python-utils
Version: 1.3.10
Summary: A python util for ubirch anchoring services.
Home-page: https://github.com/ubirch/ubirch-python-utils
Author: Michael Merz
Author-email: dermicha@ubirch.com
License: UNKNOWN
Platform: UNKNOWN
Classifier: Programming Language :: Python :: 3
Classifier: License :: OSI Approved :: Apache Software License
Classifier: Operating System :: OS Independent
Requires-Dist: kafka-python (>=1.4.3)
Requires-Dist: boto3 (>=1.7.80)
